reqmap/__init__.py
reqmap/cli.py
reqmap/dependency.py
reqmap/project.py
reqmap-0.2.0.dist-info/entry_points.txt
reqmap-0.2.0.dist-info/WHEEL
reqmap-0.2.0.dist-info/METADATA
reqmap-0.2.0.dist-info/RECORD
